twitter/__init__.py
twitter/account.py
twitter/base.py
twitter/search.py
twitter/streaming.py
twitter_api-0.1.7.dist-info/DESCRIPTION.rst
twitter_api-0.1.7.dist-info/METADATA
twitter_api-0.1.7.dist-info/RECORD
twitter_api-0.1.7.dist-info/WHEEL
twitter_api-0.1.7.dist-info/metadata.json
twitter_api-0.1.7.dist-info/top_level.txt
